img_host/__init__.py
img_host/editor.py
img_host/load.py
img_host/main.py
img_host-0.1.2.dist-info/WHEEL
img_host-0.1.2.dist-info/METADATA
img_host-0.1.2.dist-info/RECORD
