Metadata-Version: 2.1
Name: img-host
Version: 0.1.2
License: MIT
Author-email: levch <levchenko.d.a1998@gmail.com>
Requires-Python: >=3.10
Requires-Dist: httpx>=0.24.0
Requires-Dist: parsenv>=0.1.3
Requires-Dist: pillow>=9.5.0
